compphys/__init__.py
compphys/cyclotron.py
compphys/visual.py
compphys/tests/__init__.py
compphys/tests/test_cyclotron.py
scripts/__init__.py
scripts/run.py
compphys-0.0.1.dist-info/LICENSE
compphys-0.0.1.dist-info/METADATA
compphys-0.0.1.dist-info/WHEEL
compphys-0.0.1.dist-info/top_level.txt
compphys-0.0.1.dist-info/RECORD
