Metadata-Version: 2.1
Name: compphys
Version: 0.0.1
Summary: compphys
Home-page: https://github.com/JWKennington/CompPhys
Author: James Kennington
Author-email: jwkennington@psu.edu
License: MIT
Platform: UNKNOWN
Classifier: Programming Language :: Python
Classifier: Programming Language :: Python :: 3.8
Classifier: Operating System :: MacOS
Classifier: Operating System :: POSIX :: Linux
Requires-Python: ==3.7, ==3.8
Requires-Dist: matplotlib
Requires-Dist: numpy
Requires-Dist: pytest
Requires-Dist: scipy
Requires-Dist: simpy
Requires-Dist: plotly
